xmpp_backends/__init__.py
xmpp_backends/base.py
xmpp_backends/constants.py
xmpp_backends/dummy.py
xmpp_backends/ejabberd_rest.py
xmpp_backends/ejabberd_xmlrpc.py
xmpp_backends/ejabberdctl.py
xmpp_backends/django/__init__.py
xmpp_backends/django/auth_backends.py
xmpp_backends/django/models.py
xmpp_backends/django/fake_xmpp/__init__.py
xmpp_backends/django/fake_xmpp/admin.py
xmpp_backends/django/fake_xmpp/apps.py
xmpp_backends/django/fake_xmpp/backend.py
xmpp_backends/django/fake_xmpp/models.py
xmpp_backends/django/fake_xmpp/tests.py
xmpp_backends/django/fake_xmpp/views.py
xmpp_backends/django/fake_xmpp/migrations/0001_initial.py
xmpp_backends/django/fake_xmpp/migrations/__init__.py
xmpp_backends-0.8.0.dist-info/LICENSE
xmpp_backends-0.8.0.dist-info/METADATA
xmpp_backends-0.8.0.dist-info/WHEEL
xmpp_backends-0.8.0.dist-info/top_level.txt
xmpp_backends-0.8.0.dist-info/RECORD
