Metadata-Version: 2.1
Name: xmpp-backends
Version: 0.8.0
Summary: A set of classes with common interfaces to communicate with XMPP servers.
Home-page: https://github.com/mathiasertl/xmpp-backends
Author: Mathias Ertl
Author-email: mati@jabber.at
License: GNU General Public License (GPL) v3
Platform: UNKNOWN
Classifier: Development Status :: 5 - Production/Stable
Classifier: Environment :: Web Environment
Classifier: Framework :: Django
Classifier: Intended Audience :: System Administrators
Classifier: License :: OSI Approved :: GNU General Public License v3 or later (GPLv3+)
Classifier: Operating System :: OS Independent
Classifier: Programming Language :: Python
Classifier: Programming Language :: Python :: 3
Classifier: Programming Language :: Python :: 3.5
Classifier: Programming Language :: Python :: 3.6
Classifier: Programming Language :: Python :: 3.7
Classifier: Programming Language :: Python :: 3.8
Classifier: Topic :: Internet :: WWW/HTTP
Classifier: Topic :: Communications :: File Sharing
